pycolmap/__init__.py
pycolmap/_core.cpython-39-x86_64-linux-gnu.so
pycolmap/py.typed
pycolmap/utils.py
pycolmap/_core/__init__.pyi
pycolmap/_core/cost_functions.pyi
pycolmap/_core/pyceres.pyi
pycolmap/cost_functions/__init__.py
pycolmap.libs/libgfortran-83c28eba.so.5.0.0
pycolmap.libs/libgomp-e985bcbb.so.1.0.0
pycolmap.libs/libquadmath-2284e583.so.0.0.0
pycolmap-3.13.0.dist-info/METADATA
pycolmap-3.13.0.dist-info/WHEEL
pycolmap-3.13.0.dist-info/RECORD
pycolmap-3.13.0.dist-info/licenses/COPYING.txt
pycolmap-3.13.0.dist-info/sboms/auditwheel.cdx.json
